[
  {
    "DOB": "2004-07-14",
    "TOB": "07:15",
    "UTC_time": "01:45 UTC",
    "ayanamasa_Used": "Lahiri (via legacy direct flag)",
    "julian_Day": 2453200.5729166665,
    "latitude": 21.2094892,
    "location": "Surat, Gujarat, India",
    "longitude": 72.8317058,
    "nakshatra_index": 4,
    "nakshatra_name": "Rohini",
    "nakshatra_pada": 3,
    "nakshtra_all_details": {
      "deity": "Brahma (Creator God)",
      "direction": "East",
      "dosha": "Kapha",
      "fast_day": "Monday",
      "fav_alphabet": [
        "O",
        "Va",
        "Vi",
        "Vu"
      ],
      "fav_sign": "Taurus",
      "gana": "Manushya (Human)",
      "gender": "Female",
      "guna": "Rajasic",
      "mantra": "\u0950 \u0938\u094b\u092e\u093e\u092f \u0928\u092e\u0903",
      "nadi": "Antya (Kapha)",
      "pada": {
        "1": {
          "akshara": "O",
          "navamsa_sign": "Aries",
          "rashi": "Taurus"
        },
        "2": {
          "akshara": "Va",
          "navamsa_sign": "Taurus",
          "rashi": "Taurus"
        },
        "3": {
          "akshara": "Vi",
          "navamsa_sign": "Gemini",
          "rashi": "Taurus"
        },
        "4": {
          "akshara": "Vu",
          "navamsa_sign": "Cancer",
          "rashi": "Taurus"
        }
      },
      "paya": "Loha (Iron)",
      "ruling_planet": "Moon",
      "symbol": "Cart or Chariot, Temple, Banyan Tree",
      "tara": "Kshema Tara",
      "varna": "Shudra",
      "yoni": "Sarpa (Snake)"
    },
    "rashi_all_details": {
      "Taurus": {
        "body_part": "Face, Neck, Throat, Teeth",
        "direction": "South",
        "dosha": "Kapha",
        "element": "Earth",
        "gender": "Female",
        "nature": "Gentle, Steady",
        "quality": "Fixed",
        "ruler": "Venus",
        "vashya": "Chatushpada (Quadruped)"
      }
    },
    "timezone": "Asia/Kolkata",
    "tithi": "Dwadashi (Krishna Paksha (Waning))",
    "vara": "Wednesday",
    "karan": "example"
  },
  {
    "Jupiter": {
      "Avastha": "Vriddha (Old)",
      "Combust": "No",
      "DMS": "21\u00b0 27' 46\"",
      "Degree in sign": 21.46290003973047,
      "Longitude": "141.46\u00b0",
      "NakLord": "Venus",
      "Nakshatra": "Purva Phalguni",
      "Sign": "Leo",
      "SignLord": "Sun",
      "Status": "Friendly",
      "house": 5
    },
    "Ketu": {
      "Avastha": "Yuva (Adult)",
      "Combust": "No",
      "DMS": "13\u00b0 27' 19\"",
      "Degree in sign": 13.455328052325683,
      "Longitude": "193.46\u00b0",
      "NakLord": "Rahu",
      "Nakshatra": "Swati",
      "Sign": "Libra",
      "SignLord": "Venus",
      "Status": "Friendly",
      "house": 7
    },
    "Mars": {
      "Avastha": "Kumara (Teen)",
      "Combust": "No",
      "DMS": "18\u00b0 48' 26\"",
      "Degree in sign": 18.807258892004953,
      "Longitude": "108.81\u00b0",
      "NakLord": "Mercury",
      "Nakshatra": "Ashlesha",
      "Sign": "Cancer",
      "SignLord": "Moon",
      "Status": "Friendly",
      "house": 4
    },
    "Mercury": {
      "Avastha": "Kumara (Teen)",
      "Combust": "No",
      "DMS": "21\u00b0 34' 38\"",
      "Degree in sign": 21.57739052499629,
      "Longitude": "111.58\u00b0",
      "NakLord": "Mercury",
      "Nakshatra": "Ashlesha",
      "Sign": "Cancer",
      "SignLord": "Moon",
      "Status": "Enemy",
      "house": 4
    },
    "Moon": {
      "Avastha": "Kumara (Teen)",
      "Combust": "No",
      "DMS": "20\u00b0 50' 52\"",
      "Degree in sign": 20.84794852374023,
      "Longitude": "50.85\u00b0",
      "NakLord": "Moon",
      "Nakshatra": "Rohini",
      "Sign": "Taurus",
      "SignLord": "Venus",
      "Status": "Neutral",
      "house": 2
    },
    "Neptune": {
      "Avastha": "Kumara (Teen)",
      "Combust": "No",
      "DMS": "20\u00b0 40' 57\"",
      "Degree in sign": 20.682755036344588,
      "Longitude": "290.68\u00b0",
      "NakLord": "Moon",
      "Nakshatra": "Shravana",
      "Sign": "Capricorn",
      "SignLord": "Saturn",
      "Status": "Enemy",
      "house": 10
    },
    "Pluto": {
      "Avastha": "Bala (Child)",
      "Combust": "No",
      "DMS": "26\u00b0 10' 48\"",
      "Degree in sign": 26.180197483422745,
      "Longitude": "236.18\u00b0",
      "NakLord": "Mercury",
      "Nakshatra": "Jyeshtha",
      "Sign": "Scorpio",
      "SignLord": "Mars",
      "Status": "Friendly",
      "house": 8
    },
    "Rahu": {
      "Avastha": "Yuva (Adult)",
      "Combust": "No",
      "DMS": "13\u00b0 27' 19\"",
      "Degree in sign": 13.455328052325678,
      "Longitude": "13.46\u00b0",
      "NakLord": "Venus",
      "Nakshatra": "Bharani",
      "Sign": "Aries",
      "SignLord": "Mars",
      "Status": "--",
      "house": 1
    },
    "Saturn": {
      "Avastha": "Vriddha (Old)",
      "Combust": "Yes",
      "DMS": "23\u00b0 36' 41\"",
      "Degree in sign": 23.611654686159497,
      "Longitude": "83.61\u00b0",
      "NakLord": "Jupiter",
      "Nakshatra": "Punarvasu",
      "Sign": "Gemini",
      "SignLord": "Mercury",
      "Status": "Friendly",
      "house": 3
    },
    "Sun": {
      "Avastha": "Mrita (Dead)",
      "Combust": "No",
      "DMS": "28\u00b0 2' 37\"",
      "Degree in sign": 28.043845148242724,
      "Longitude": "88.04\u00b0",
      "NakLord": "Jupiter",
      "Nakshatra": "Punarvasu",
      "Sign": "Gemini",
      "SignLord": "Mercury",
      "Status": "Neutral",
      "house": 3
    },
    "Uranus": {
      "Avastha": "Yuva (Adult)",
      "Combust": "No",
      "DMS": "12\u00b0 26' 52\"",
      "Degree in sign": 12.448042012709777,
      "Longitude": "312.45\u00b0",
      "NakLord": "Rahu",
      "Nakshatra": "Shatabhisha",
      "Sign": "Aquarius",
      "SignLord": "Saturn",
      "Status": "Friendly",
      "house": 11
    },
    "Venus": {
      "Avastha": "Kumara (Teen)",
      "Combust": "No",
      "DMS": "19\u00b0 10' 17\"",
      "Degree in sign": 19.1714409150115,
      "Longitude": "49.17\u00b0",
      "NakLord": "Moon",
      "Nakshatra": "Rohini",
      "Sign": "Taurus",
      "SignLord": "Venus",
      "Status": "Own Sign",
      "house": 2
    }
  }
]
